alidanotebookutils/__init__.py
alidanotebookutils/files.py
alidanotebookutils/pandasAssets.py
alidanotebookutils/sparkAssets.py
alidanotebookutils/asset/__init__.py
alidanotebookutils/asset/asset.py
alidanotebookutils/asset/dataset.py
alidanotebookutils/asset/model.py
alidanotebookutils/asset/model_storage/__init__.py
alidanotebookutils/asset/model_storage/generic_storage.py
alidanotebookutils/asset/model_storage/hdfs.py
alidanotebookutils/asset/model_storage/minio.py
alidanotebookutils/asset/model_storage/utils.py
alidanotebookutils/asset/storage/__init__.py
alidanotebookutils/asset/storage/hive.py
alidanotebookutils/asset/storage/minio.py
alidanotebookutils/asset/storage/storage.py
alidanotebookutils/asset/storage/test.py
alidanotebookutils/asset/storage/utils.py
alida_notebook_utils-0.0.1.dist-info/METADATA
alida_notebook_utils-0.0.1.dist-info/WHEEL
alida_notebook_utils-0.0.1.dist-info/top_level.txt
alida_notebook_utils-0.0.1.dist-info/RECORD
